MANIFEST.in
setup.cfg
setup.py
addattr/__init__.py
addattr/models.py
addattr/templatetags/__init__.py
addattr/templatetags/addattr.py
djangoaddattr.egg-info/PKG-INFO
djangoaddattr.egg-info/SOURCES.txt
djangoaddattr.egg-info/dependency_links.txt
djangoaddattr.egg-info/not-zip-safe
djangoaddattr.egg-info/requires.txt
djangoaddattr.egg-info/top_level.txt