Metadata-Version: 1.1
Name: djangoaddattr
Version: 0.0.1
Summary: djangoaddattr
Home-page: http://github.com/neuman/django-template-addattr
Author: neuman
Author-email: soloptimus@gmail.com
License: BSD
Keywords: bootstrap,django
Platform: UNKNOWN
Classifier: Programming Language :: Python
Classifier: Topic :: Software Development :: Libraries :: Python Modules
Classifier: Framework :: Django
Classifier: Environment :: Web Environment
Classifier: Programming Language :: Python :: 2
Classifier: Programming Language :: Python :: 2.7
Classifier: Programming Language :: Python :: 3
Classifier: Programming Language :: Python :: 3.3
Classifier: Programming Language :: Python :: 3.4
